EC-P01-SesionesTutorizadas/src/ha_vr.v
module ha_vr(output wire sum, output wire carry, input wire a, input wire b);
  // La salida se actualizará una unidad de tipo después de que cambien a y b.
  xor #(1) xor_1(sum,a,b);
  and #(1) and_1(carry,a,b);
endmodule

EC-P01-SesionesTutorizadas/src/fa_vr.v
`include "ha_vr.v" 

module fa_vr(input wire c_in, input wire a, input wire b, output wire sum, output wire c_out);
  wire sum1, carry_1, carry_2;

  ha_vr half_adder_1(
    .a(a), 
    .b(b), 
    .sum(sum1), 
    .carry(carry_1)
  );

  ha_vr half_adder_2(
    .a(sum1), 
    .b(c_in), 
    .sum(sum), 
    .carry(carry_2)
  );

  or or_1(c_out, carry_1, carry_2);
endmodule

EC-P01-SesionesTutorizadas/tb/fa_vr_tb.v
`timescale 1ns/1ps
`include "../src/fa_vr.v"

module fa_vr_tb; 
  reg test_a, test_b, test_cin;
  wire test_sum, test_carry;

  fa_vr full_adder(
    .c_in(test_cin),
    .a(test_a),
    .b(test_b),
    .sum(test_sum), 
    .c_out(test_carry)
  ); 

  initial begin
    $dumpfile("fa_vr_tb.vcd");
    $dumpvars;
    $monitor("tiempo=%t, a=%b, b=%b, acarreo_entrada=%b, suma=%b, acarreo_salida=%b", $time, test_a, test_b, test_cin, test_sum, test_carry);

    test_a = 'b0;
    test_b = 'b0;
    test_cin = 'b0;
    #20; 

    test_a = 'b0;
    test_b = 'b0;
    test_cin = 'b1;
    #20;

    test_a = 'b0;
    test_b = 'b1;
    test_cin = 'b0;
    #20;

    test_a = 'b0;
    test_b = 'b1;
    test_cin = 'b1;
    #20;

    test_a = 'b1;
    test_b = 'b0;
    test_cin = 'b0;
    #20;

    test_a = 'b1;
    test_b = 'b0;
    test_cin = 'b1;
    #20;

    test_a = 'b1;
    test_b = 'b1;
    test_cin = 'b0;
    #20;

    test_a = 'b1;
    test_b = 'b1;
    test_cin = 'b1;
    #20;

    $finish; 
  end

endmodule

EC-P01-SesionesTutorizadas/build/fa_vr_tb.vcd
$date
	Wed Sep 16 16:15:09 2026
$end
$version
	Icarus Verilog
$end
$timescale
	1ps
$end
$scope module fa_vr_tb $end
$var wire 1 ! test_sum $end
$var wire 1 " test_carry $end
$var reg 1 # test_a $end
$var reg 1 $ test_b $end
$var reg 1 % test_cin $end
$scope module full_adder $end
$var wire 1 # a $end
$var wire 1 $ b $end
$var wire 1 % c_in $end
$var wire 1 " c_out $end
$var wire 1 & sum1 $end
$var wire 1 ! sum $end
$var wire 1 ' carry_2 $end
$var wire 1 ( carry_1 $end
$scope module half_adder_1 $end
$var wire 1 # a $end
$var wire 1 $ b $end
$var wire 1 ( carry $end
$var wire 1 & sum $end
$upscope $end
$scope module half_adder_2 $end
$var wire 1 & a $end
$var wire 1 % b $end
$var wire 1 ' carry $end
$var wire 1 ! sum $end
$upscope $end
$upscope $end
$upscope $end
$enddefinitions $end
$comment Show the parameter values. $end
$dumpall
$end
#0
$dumpvars
x(
x'
x&
0%
0$
0#
x"
x!
$end
#1000
0"
0'
0(
0&
#2000
0!
#20000
1%
#21000
1!
#40000
0%
1$
#41000
0!
1&
#42000
1!
#60000
1%
#61000
1"
0!
1'
#80000
0%
0$
1#
#81000
0"
1!
0'
#100000
1%
#101000
1"
0!
1'
#120000
0%
1$
#121000
1!
0'
0&
1(
#122000
0!
#140000
1%
#141000
1!
